odoo8_addon_mail_notification_email_template-8.0.1.0.0.99.dev13-py2.7-nspkg.pth
odoo8_addon_mail_notification_email_template-8.0.1.0.0.99.dev13.dist-info/METADATA
odoo8_addon_mail_notification_email_template-8.0.1.0.0.99.dev13.dist-info/RECORD
odoo8_addon_mail_notification_email_template-8.0.1.0.0.99.dev13.dist-info/WHEEL
odoo8_addon_mail_notification_email_template-8.0.1.0.0.99.dev13.dist-info/namespace_packages.txt
odoo8_addon_mail_notification_email_template-8.0.1.0.0.99.dev13.dist-info/top_level.txt
odoo_addons/mail_notification_email_template/README.rst
odoo_addons/mail_notification_email_template/__init__.py
odoo_addons/mail_notification_email_template/__openerp__.py
odoo_addons/mail_notification_email_template/data/email_template.xml
odoo_addons/mail_notification_email_template/data/mail_message_subtype.xml
odoo_addons/mail_notification_email_template/i18n/ca.po
odoo_addons/mail_notification_email_template/i18n/de.po
odoo_addons/mail_notification_email_template/i18n/el_GR.po
odoo_addons/mail_notification_email_template/i18n/es.po
odoo_addons/mail_notification_email_template/i18n/fi.po
odoo_addons/mail_notification_email_template/i18n/fr.po
odoo_addons/mail_notification_email_template/i18n/it.po
odoo_addons/mail_notification_email_template/i18n/mail_notification_email_template.pot
odoo_addons/mail_notification_email_template/i18n/pt_BR.po
odoo_addons/mail_notification_email_template/i18n/sl.po
odoo_addons/mail_notification_email_template/i18n/zh_CN.po
odoo_addons/mail_notification_email_template/models/__init__.py
odoo_addons/mail_notification_email_template/models/mail_message_subtype.py
odoo_addons/mail_notification_email_template/models/mail_notification.py
odoo_addons/mail_notification_email_template/static/description/icon.png
odoo_addons/mail_notification_email_template/tests/__init__.py
odoo_addons/mail_notification_email_template/tests/test_mail_notification_email_template.py
odoo_addons/mail_notification_email_template/views/mail_message_subtype.xml
